examples/example1.py
examples/example2.py
simple_observable/__init__.py
simple_observable/observable.py
tests/__init__.py
simple_observable-0.1.0.dist-info/LICENSE
simple_observable-0.1.0.dist-info/METADATA
simple_observable-0.1.0.dist-info/WHEEL
simple_observable-0.1.0.dist-info/top_level.txt
simple_observable-0.1.0.dist-info/RECORD
