Metadata-Version: 2.1
Name: simple-observable
Version: 0.1.0
Summary: A simple observer pattern implementation
Author-email: darkhaniop <darkhaniop@google.com>
Project-URL: Homepage, https://github.com/gw-tools/simple-observable
Project-URL: Bug Tracker, https://github.com/gw-tools/simple-observable/issues
Keywords: observer,observable
Classifier: Intended Audience :: Developers
Classifier: Programming Language :: Python :: 3
Classifier: License :: OSI Approved :: MIT License
Classifier: Operating System :: OS Independent
Requires-Python: <4,>=3.7
License-File: LICENSE
